omniscient/__init__.py
omniscient/run.py
omniscient-0.1.dist-info/METADATA
omniscient-0.1.dist-info/WHEEL
omniscient-0.1.dist-info/top_level.txt
omniscient-0.1.dist-info/RECORD
