Metadata-Version: 2.1
Name: omniscient
Version: 0.1
Summary: Omniscient question answering system
Home-page: UNKNOWN
Author: Pasan Karunaratne
Author-email: pasankarunaratne@gmail.com
License: MIT
Platform: UNKNOWN
Requires-Dist: scikit-learn
Requires-Dist: pandas
Requires-Dist: deeppavlov
